CONTRIBUTING.md
LICENSE
MANIFEST.in
README.md
setup.cfg
setup.py
docs/Makefile
docs/conf.py
docs/contributing.rst
docs/index.rst
docs/installation.rst
docs/make.bat
homewizard_climate_ws/__init__.py
homewizard_climate_ws/const.py
homewizard_climate_ws/debug.py
homewizard_climate_ws/main.py
homewizard_climate_ws.egg-info/PKG-INFO
homewizard_climate_ws.egg-info/SOURCES.txt
homewizard_climate_ws.egg-info/dependency_links.txt
homewizard_climate_ws.egg-info/not-zip-safe
homewizard_climate_ws.egg-info/requires.txt
homewizard_climate_ws.egg-info/top_level.txt
homewizard_climate_ws/api/__init__.py
homewizard_climate_ws/api/api.py
homewizard_climate_ws/model/__init__.py
homewizard_climate_ws/model/climate_device.py
homewizard_climate_ws/model/climate_device_state.py
homewizard_climate_ws/ws/__init__.py
homewizard_climate_ws/ws/hw_websocket.py
homewizard_climate_ws/ws/hw_websocket_payloads.py
tests/__init__.py
tests/conftest.py
tests/test_dummy.py
tests/data/example_values.json