Metadata-Version: 2.1
Name: homewizard-climate-ws
Version: 0.0.21
Summary: API/Websocket to control Homewizard Climate devices
Home-page: https://github.com/dennis1804/homewizard-climate-websocket
Author: Dennis1804
Author-email: dennis@de-jong.frl
License: MIT license
Keywords: homewizard_climate_ws
Classifier: Development Status :: 2 - Pre-Alpha
Classifier: Intended Audience :: Developers
Classifier: License :: OSI Approved :: MIT License
Classifier: Natural Language :: English
Classifier: Programming Language :: Python :: 3.7
Classifier: Programming Language :: Python :: 3.8
Classifier: Programming Language :: Python :: 3.9
Classifier: Programming Language :: Python :: 3.10
Requires-Python: >=3.7
Provides-Extra: setup
Provides-Extra: test
Provides-Extra: dev
Provides-Extra: all
License-File: LICENSE
